setup.py
PyMicrotops/__init__.py
PyMicrotops/microtops.py
PyMicrotops/read_from_serial.py
PyMicrotops.egg-info/PKG-INFO
PyMicrotops.egg-info/SOURCES.txt
PyMicrotops.egg-info/dependency_links.txt
PyMicrotops.egg-info/entry_points.txt
PyMicrotops.egg-info/requires.txt
PyMicrotops.egg-info/top_level.txt