Metadata-Version: 1.1
Name: PyMicrotops
Version: 1.1.0
Summary: A module to read and process data from the Microtops sun photometer, including reading via serial link and interpolating to AOT at any wavelength
Home-page: https://github.com/robintw/PyMicrotops
Author: Robin Wilson
Author-email: robin@rtwilson.com
License: BSC
Platform: UNKNOWN
Classifier: Development Status :: 5 - Production/Stable
Classifier: Intended Audience :: Science/Research
Classifier: Topic :: Scientific/Engineering :: Atmospheric Science
Classifier: Topic :: Scientific/Engineering :: Physics
Classifier: Topic :: Software Development :: Libraries :: Python Modules
Classifier: License :: OSI Approved :: BSD License
Classifier: Programming Language :: Python
Classifier: Programming Language :: Python :: 3
Classifier: Programming Language :: Python :: 2
